st_wallet_connect/__init__.py
st_wallet_connect/frontend/build/asset-manifest.json
st_wallet_connect/frontend/build/index.html
st_wallet_connect/frontend/build/precache-manifest.c4dd49f4c025a7102c4854b28c98a964.js
st_wallet_connect/frontend/build/service-worker.js
st_wallet_connect/frontend/build/static/css/main.7a75ab8c.chunk.css
st_wallet_connect/frontend/build/static/css/main.7a75ab8c.chunk.css.map
st_wallet_connect/frontend/build/static/js/0.9ebdf84a.chunk.js
st_wallet_connect/frontend/build/static/js/0.9ebdf84a.chunk.js.LICENSE.txt
st_wallet_connect/frontend/build/static/js/0.9ebdf84a.chunk.js.map
st_wallet_connect/frontend/build/static/js/3.b82772fe.chunk.js
st_wallet_connect/frontend/build/static/js/3.b82772fe.chunk.js.LICENSE.txt
st_wallet_connect/frontend/build/static/js/3.b82772fe.chunk.js.map
st_wallet_connect/frontend/build/static/js/4.caf6a9ac.chunk.js
st_wallet_connect/frontend/build/static/js/4.caf6a9ac.chunk.js.map
st_wallet_connect/frontend/build/static/js/5.59e9ce86.chunk.js
st_wallet_connect/frontend/build/static/js/5.59e9ce86.chunk.js.LICENSE.txt
st_wallet_connect/frontend/build/static/js/5.59e9ce86.chunk.js.map
st_wallet_connect/frontend/build/static/js/6.b3fcad8e.chunk.js
st_wallet_connect/frontend/build/static/js/6.b3fcad8e.chunk.js.map
st_wallet_connect/frontend/build/static/js/7.b552d2cc.chunk.js
st_wallet_connect/frontend/build/static/js/7.b552d2cc.chunk.js.map
st_wallet_connect/frontend/build/static/js/main.019c44a5.chunk.js
st_wallet_connect/frontend/build/static/js/main.019c44a5.chunk.js.map
st_wallet_connect/frontend/build/static/js/runtime-main.056501e2.js
st_wallet_connect/frontend/build/static/js/runtime-main.056501e2.js.map
st_wallet_connect/frontend/build/static/media/Coinbase-icon-symbol-1.3ee013be.png
st_wallet_connect/frontend/build/static/media/Metamask-icon.bca3db3e.png
st_wallet_connect-0.9.0.dist-info/LICENSE
st_wallet_connect-0.9.0.dist-info/METADATA
st_wallet_connect-0.9.0.dist-info/WHEEL
st_wallet_connect-0.9.0.dist-info/top_level.txt
st_wallet_connect-0.9.0.dist-info/RECORD
