Metadata-Version: 2.1
Name: st_wallet_connect
Version: 0.9.0
Summary: Streamlit component that allows you to use walletconnect/web3modal
Home-page: https://github.com/webcoderz/st-wallet-connect
Author: Cody Webb
Author-email: cody.l.webb@gmail.com
Requires-Python: >=3.7
License-File: LICENSE
Requires-Dist: streamlit >=0.63
Provides-Extra: devel
Requires-Dist: wheel ; extra == 'devel'
Requires-Dist: pytest ==7.4.0 ; extra == 'devel'
Requires-Dist: playwright ==1.39.0 ; extra == 'devel'
Requires-Dist: requests ==2.31.0 ; extra == 'devel'
Requires-Dist: pytest-playwright-snapshot ==1.0 ; extra == 'devel'
Requires-Dist: pytest-rerunfailures ==12.0 ; extra == 'devel'
